setup.py
wunderlist/__init__.py
wunderlist/wunderlist.py
wunderlist.egg-info/PKG-INFO
wunderlist.egg-info/SOURCES.txt
wunderlist.egg-info/dependency_links.txt
wunderlist.egg-info/not-zip-safe
wunderlist.egg-info/top_level.txt