Metadata-Version: 1.0
Name: wunderlist
Version: 0.1
Summary: Wunderlist API in Python
Home-page: http://github.com/hameedullah/python-wunderlist
Author: Hameedullah Khan
Author-email: h@hameedullah.com
License: MIT
Platform: UNKNOWN
